{
  "first_write_date": {
    "y": 2014,
    "m": 6,
    "d": 10
  },
  "id": {
    "game_character_id": 21569,
    "character_variant": 84,
    "figure_type": 82,
    "model_number": 65535,
    "series": 254
  },
  "last_write_date": {
    "y": 2014,
    "m": 6,
    "d": 10
  },
  "mii_charinfo_file": "mii-charinfo.bin",
  "name": "emuiibo_1",
  "uuid": [
    0,
    5,
    22,
    7,
    0,
    2,
    0,
    0,
    77,
    97
  ],
  "use_random_uuid": false,
  "version": 0,
  "write_counter": 0
}